trove_tempest_plugin/__init__.py
trove_tempest_plugin/config.py
trove_tempest_plugin/plugin.py
trove_tempest_plugin/services/__init__.py
trove_tempest_plugin/services/client.py
trove_tempest_plugin/tests/__init__.py
trove_tempest_plugin/tests/base.py
trove_tempest_plugin/tests/constants.py
trove_tempest_plugin/tests/exceptions.py
trove_tempest_plugin/tests/utils.py
trove_tempest_plugin/tests/scenario/__init__.py
trove_tempest_plugin/tests/scenario/base_actions.py
trove_tempest_plugin/tests/scenario/base_backup.py
trove_tempest_plugin/tests/scenario/base_basic.py
trove_tempest_plugin/tests/scenario/base_cinder_backup.py
trove_tempest_plugin/tests/scenario/base_replication.py
trove_tempest_plugin/tests/scenario/base_update_access.py
trove_tempest_plugin/tests/scenario/test_backup.py
trove_tempest_plugin/tests/scenario/test_cinder_backup.py
trove_tempest_plugin/tests/scenario/test_instance_actions.py
trove_tempest_plugin/tests/scenario/test_instance_basic.py
trove_tempest_plugin/tests/scenario/test_instance_update_access.py
trove_tempest_plugin/tests/scenario/test_replication.py
trove_tempest_plugin-2.6.0.dist-info/AUTHORS
trove_tempest_plugin-2.6.0.dist-info/LICENSE
trove_tempest_plugin-2.6.0.dist-info/METADATA
trove_tempest_plugin-2.6.0.dist-info/WHEEL
trove_tempest_plugin-2.6.0.dist-info/entry_points.txt
trove_tempest_plugin-2.6.0.dist-info/pbr.json
trove_tempest_plugin-2.6.0.dist-info/top_level.txt
trove_tempest_plugin-2.6.0.dist-info/RECORD
