Metadata-Version: 2.1
Name: trove_tempest_plugin
Version: 2.6.0
Summary: Tempest plugin for Trove project
Home-page: https://docs.openstack.org/trove/latest/
Author: OpenStack
Author-email: openstack-discuss@lists.openstack.org
Classifier: Environment :: OpenStack
Classifier: Intended Audience :: Information Technology
Classifier: Intended Audience :: System Administrators
Classifier: License :: OSI Approved :: Apache Software License
Classifier: Operating System :: POSIX :: Linux
Classifier: Programming Language :: Python
Classifier: Programming Language :: Python :: Implementation :: CPython
Classifier: Programming Language :: Python :: 3 :: Only
Classifier: Programming Language :: Python :: 3
Classifier: Programming Language :: Python :: 3.9
Classifier: Programming Language :: Python :: 3.10
Classifier: Programming Language :: Python :: 3.11
Classifier: Programming Language :: Python :: 3.12
Requires-Python: >= 3.9
License-File: LICENSE
License-File: AUTHORS
Requires-Dist: pbr !=2.1.0,>=2.0.0
Requires-Dist: oslo.config >=5.2.0
Requires-Dist: oslo.log >=3.44.1
Requires-Dist: oslo.serialization >=2.29.1
Requires-Dist: oslo.service >=1.40.1
Requires-Dist: oslotest >=3.2.0
Requires-Dist: requests >=2.14.2
Requires-Dist: tempest >=17.1.0
Requires-Dist: tenacity >=5.1.1
Requires-Dist: SQLAlchemy >=1.4.0
Requires-Dist: PyMySQL >=0.7.6
Requires-Dist: psycopg2-binary >=2.6.2
Requires-Dist: python-swiftclient >=3.2.0
